MANIFEST.in
README.rst
setup.py
django_sendgrid_local.egg-info/PKG-INFO
django_sendgrid_local.egg-info/SOURCES.txt
django_sendgrid_local.egg-info/dependency_links.txt
django_sendgrid_local.egg-info/top_level.txt
local_sendgrid/__init__.py
local_sendgrid/admin.py
local_sendgrid/tests.py
local_sendgrid/urls.py
local_sendgrid/views.py
local_sendgrid/migrations/0001_initial.py
local_sendgrid/migrations/0002_transactional.py
local_sendgrid/migrations/0003_auto_20170608_2155.py
local_sendgrid/migrations/0005_auto_20170609_1623.py
local_sendgrid/migrations/0006_auto_20170616_1349.py
local_sendgrid/migrations/0007_auto_20170616_1349.py
local_sendgrid/migrations/0008_remove_transactionalemail_recipient.py
local_sendgrid/migrations/__init__.py
local_sendgrid/models/__init__.py
local_sendgrid/models/events.py
local_sendgrid/models/models.py