Metadata-Version: 1.1
Name: django-sendgrid-local
Version: 0.2.4
Summary: A simple Django app to use sendgrid and store local copy.
Home-page: https://github.com/MasAval/django_sendgrid
Author: Alvaro Saavedra
Author-email: asaavedra@masaval.cl
License: BSD License
Platform: UNKNOWN
Classifier: Environment :: Web Environment
Classifier: Framework :: Django
Classifier: Framework :: Django :: 1.8
Classifier: Intended Audience :: Developers
Classifier: License :: OSI Approved :: BSD License
Classifier: Operating System :: OS Independent
Classifier: Programming Language :: Python
Classifier: Programming Language :: Python :: 2
Classifier: Topic :: Internet :: WWW/HTTP
Classifier: Topic :: Internet :: WWW/HTTP :: Dynamic Content
